teleinfo/__init__.py
teleinfo/main.py
teleget-0.2.0.dist-info/METADATA
teleget-0.2.0.dist-info/WHEEL
teleget-0.2.0.dist-info/top_level.txt
teleget-0.2.0.dist-info/RECORD
